psitip/__init__.py
psitip/__main__.py
psitip/psitip.py
psitip-1.1.7.dist-info/METADATA
psitip-1.1.7.dist-info/WHEEL
psitip-1.1.7.dist-info/licenses/LICENSE
psitip-1.1.7.dist-info/RECORD
