Metadata-Version: 2.4
Name: psitip
Version: 1.1.7
Summary: Python Symbolic Information Theoretic Inequality Prover
Project-URL: Homepage, https://github.com/cheuktingli/psitip
Project-URL: Bug Tracker, https://github.com/cheuktingli/psitip/issues
Author-email: Cheuk Ting Li <ctli@ie.cuhk.edu.hk>
License:                     GNU GENERAL PUBLIC LICENSE
License-File: LICENSE
Classifier: Intended Audience :: Science/Research
Classifier: License :: OSI Approved :: GNU General Public License v3 (GPLv3)
Classifier: Operating System :: OS Independent
Classifier: Programming Language :: Python :: 3
Classifier: Topic :: Scientific/Engineering
Classifier: Topic :: Scientific/Engineering :: Mathematics
Requires-Python: >=3.7
Requires-Dist: graphviz
Requires-Dist: lark-parser
Requires-Dist: matplotlib
Requires-Dist: numpy
Requires-Dist: ortools
Requires-Dist: pycddlib
Requires-Dist: pylatexenc
Requires-Dist: scipy
Requires-Dist: torch
